perkeepy/__init__.py
perkeepy/test_bogus.py
perkeepy-0.1.7.dist-info/LICENSE
perkeepy-0.1.7.dist-info/METADATA
perkeepy-0.1.7.dist-info/WHEEL
perkeepy-0.1.7.dist-info/top_level.txt
perkeepy-0.1.7.dist-info/RECORD
